tacview_duckdb/__init__.py
tacview_duckdb/__version__.py
tacview_duckdb/api.py
tacview_duckdb/cli/__init__.py
tacview_duckdb/cli/main.py
tacview_duckdb/enrichment/__init__.py
tacview_duckdb/enrichment/airports.py
tacview_duckdb/enrichment/coalitions.py
tacview_duckdb/enrichment/containers.py
tacview_duckdb/enrichment/decoys.py
tacview_duckdb/enrichment/ejection_events.py
tacview_duckdb/enrichment/geocoding.py
tacview_duckdb/enrichment/geodata.py
tacview_duckdb/enrichment/lifecycle.py
tacview_duckdb/enrichment/missed_weapons.py
tacview_duckdb/enrichment/pipeline.py
tacview_duckdb/enrichment/projectile.py
tacview_duckdb/enrichment/relationships.py
tacview_duckdb/enrichment/spatial_clusters.py
tacview_duckdb/enrichment/weapons.py
tacview_duckdb/parser/__init__.py
tacview_duckdb/parser/acmi_parser.py
tacview_duckdb/parser/type_parser.py
tacview_duckdb/parser/types.py
tacview_duckdb/parser/utils.py
tacview_duckdb/storage/__init__.py
tacview_duckdb/storage/duckdb_store.py
tacview_duckdb/storage/hash_utils.py
tacview_duckdb/storage/schema.py
tacview_duckdb-0.1.2.dist-info/licenses/LICENSE
tacview_duckdb-0.1.2.dist-info/METADATA
tacview_duckdb-0.1.2.dist-info/WHEEL
tacview_duckdb-0.1.2.dist-info/entry_points.txt
tacview_duckdb-0.1.2.dist-info/top_level.txt
tacview_duckdb-0.1.2.dist-info/RECORD
