Metadata-Version: 2.4
Name: tacview-duckdb
Version: 0.1.2
Summary: Parse Tacview ACMI files into DuckDB database with kinematic analysis
Author: Tacview DuckDB Contributors
License: MIT
Project-URL: Homepage, https://github.com/uriba107/tacview-duckdb
Project-URL: Repository, https://github.com/uriba107/tacview-duckdb
Classifier: Development Status :: 3 - Alpha
Classifier: Intended Audience :: Developers
Classifier: License :: OSI Approved :: MIT License
Classifier: Programming Language :: Python :: 3
Classifier: Programming Language :: Python :: 3.8
Classifier: Programming Language :: Python :: 3.9
Classifier: Programming Language :: Python :: 3.10
Classifier: Programming Language :: Python :: 3.11
Classifier: Programming Language :: Python :: 3.12
Requires-Python: >=3.8
License-File: LICENSE
Requires-Dist: duckdb>=1.4.1
Requires-Dist: pyarrow>=15.0.0
Requires-Dist: numpy>=1.20.0
Requires-Dist: geopy>=2.3.0
Requires-Dist: python-dotenv>=0.19.0
Requires-Dist: chardet>=5.0.0
Provides-Extra: dev
Requires-Dist: pytest>=7.0.0; extra == "dev"
Requires-Dist: pytest-cov>=4.0.0; extra == "dev"
Requires-Dist: black>=23.0.0; extra == "dev"
Requires-Dist: ruff>=0.1.0; extra == "dev"
Requires-Dist: mypy>=1.0.0; extra == "dev"
Dynamic: license-file
